ur_audio_sub/__init__.py
ur_audio_sub/caption_generator.py
ur_audio_sub-0.0.6.dist-info/LICENSE
ur_audio_sub-0.0.6.dist-info/METADATA
ur_audio_sub-0.0.6.dist-info/WHEEL
ur_audio_sub-0.0.6.dist-info/top_level.txt
ur_audio_sub-0.0.6.dist-info/RECORD
