Metadata-Version: 2.1
Name: ur-audio-sub
Version: 0.0.6
Summary: Generate text captions for audio files & youtube video using OpenAI Whisper. Multiple languages support.
Home-page: https://github.com/thinh-vu/ur_audio_sub
Author: Thinh Vu
Author-email: mrthinh@live.com
Classifier: Programming Language :: Python :: 3
Classifier: License :: OSI Approved :: MIT License
Classifier: Operating System :: OS Independent
Requires-Python: >=3.7
License-File: LICENSE
Requires-Dist: pytube
Requires-Dist: ffmpeg-python
Requires-Dist: ur-gadget
